README.md
setup.py
fuzzy/__init__.py
fuzzy/__main__.py
fuzzy/cli.py
fuzzy/fuzzy.py
fuzzy/logging.py
fuzzy/matching.py
fuzzy/printer.py
fuzzy/request.py
fuzzy/utils.py
fuzzyfuzzer.egg-info/PKG-INFO
fuzzyfuzzer.egg-info/SOURCES.txt
fuzzyfuzzer.egg-info/dependency_links.txt
fuzzyfuzzer.egg-info/entry_points.txt
fuzzyfuzzer.egg-info/requires.txt
fuzzyfuzzer.egg-info/top_level.txt