Metadata-Version: 1.0
Name: fuzzyfuzzer
Version: 0.0.8
Summary: Fuzzy - An other web fuzzer
Home-page: https://github.com/SakiiR/fuzzy
Author: SakiiR SakiiR (@SakiiR)
Author-email: UNKNOWN
License: UNKNOWN
Platform: UNKNOWN
